pyplatter/__init__.py
pyplatter/platter.py
pyplatter/py.typed
pyplatter-1.0.0.dist-info/LICENSE
pyplatter-1.0.0.dist-info/METADATA
pyplatter-1.0.0.dist-info/WHEEL
pyplatter-1.0.0.dist-info/top_level.txt
pyplatter-1.0.0.dist-info/RECORD
